benchmarks/__init__.py
tests/__init__.py
tests/test_import.py
tests/test_sanity.py
trolls/__init__.py
trolls/moving_average_threshold.py
trolls/multiple_environments_wrapper.py
trolls/render_mode.py
trolls/spaces_mixin.py
trolls/vector_environments.py
trolls/experimental/__init__.py
trolls/experimental/cloud_pickle_wrapper.py
trolls/experimental/normalised_state.py
trolls/experimental/sub_process_vector_environments.py
trolls/gym_wrappers/__init__.py
trolls/gym_wrappers/bonus.py
trolls/gym_wrappers/buffered.py
trolls/gym_wrappers/clipped.py
trolls/gym_wrappers/no_termination.py
trolls/gym_wrappers/noisy.py
trolls/gym_wrappers/normalised.py
trolls/gym_wrappers/skip.py
trolls/gym_wrappers/space.py
trolls/gym_wrappers/time_limited.py
trolls/gym_wrappers/img_obs/__init__.py
trolls/gym_wrappers/img_obs/grayscale.py
trolls/gym_wrappers/img_obs/resize.py
trolls/spaces/__init__.py
trolls/spaces/action_space.py
trolls/spaces/observation_space.py
trolls/spaces/range.py
trolls/spaces/signal_space.py
trolls/spaces/space.py
trolls/spaces/vector/__init__.py
trolls/spaces/vector/vector_action_space.py
trolls/spaces/vector/vector_observation_space.py
trolls/spaces/vector/vector_signal_space.py
Trolls-0.3.5.dist-info/LICENSE.md
Trolls-0.3.5.dist-info/METADATA
Trolls-0.3.5.dist-info/WHEEL
Trolls-0.3.5.dist-info/entry_points.txt
Trolls-0.3.5.dist-info/top_level.txt
Trolls-0.3.5.dist-info/RECORD
