Metadata-Version: 2.1
Name: Trolls
Version: 0.3.5
Summary: Hidden monsters
Home-page: https://github.com/cnheider/trolls
Author: Christian Heider Nielsen
Author-email: christian.heider@alexandra.dk
Maintainer: Christian Heider Nielsen
Maintainer-email: christian.heider@alexandra.dk
License: Apache License, Version 2.0
Download-URL: https://github.com/cnheider/trolls/releases
Keywords: python reinforcement-learning interface api
Platform: UNKNOWN
Classifier: Development Status :: 4 - Beta
Classifier: Environment :: Console
Classifier: Intended Audience :: End Users/Desktop
Classifier: Intended Audience :: Developers
Classifier: License :: OSI Approved :: Apache Software License
Classifier: Operating System :: MacOS :: MacOS X
Classifier: Operating System :: Microsoft :: Windows
Classifier: Operating System :: POSIX
Classifier: Operating System :: OS Independent
Classifier: Programming Language :: Python :: 3
Classifier: Natural Language :: English
Requires-Python: >=3.6
License-File: LICENSE.md
Requires-Dist: numpy
Requires-Dist: six
Requires-Dist: scikit-image
Requires-Dist: sorcery
Requires-Dist: draugr[drawers]
Requires-Dist: gym
Requires-Dist: cloudpickle
Requires-Dist: pytest
Provides-Extra: all
Requires-Dist: trolls ; extra == 'all'
Requires-Dist: mistune (<2.0.0) ; extra == 'all'
Requires-Dist: pytest (>=4.4.1) ; extra == 'all'
Requires-Dist: pip (>=19.0.3) ; extra == 'all'
Requires-Dist: pytest (>=4.3.0) ; extra == 'all'
Requires-Dist: m2r2 ; extra == 'all'
Requires-Dist: draugr ; extra == 'all'
Requires-Dist: sphinxcontrib-programoutput ; extra == 'all'
Requires-Dist: black (>=18.9b0) ; extra == 'all'
Requires-Dist: twine (>=1.13.0) ; extra == 'all'
Requires-Dist: coveralls (>=1.6.0) ; extra == 'all'
Requires-Dist: wheel (>=0.33.0) ; extra == 'all'
Requires-Dist: pytest-cov (>=2.6.1) ; extra == 'all'
Provides-Extra: dev
Requires-Dist: trolls ; extra == 'dev'
Requires-Dist: mistune (<2.0.0) ; extra == 'dev'
Requires-Dist: pytest (>=4.4.1) ; extra == 'dev'
Requires-Dist: pip (>=19.0.3) ; extra == 'dev'
Requires-Dist: pytest (>=4.3.0) ; extra == 'dev'
Requires-Dist: black (>=18.9b0) ; extra == 'dev'
Requires-Dist: twine (>=1.13.0) ; extra == 'dev'
Requires-Dist: m2r2 ; extra == 'dev'
Requires-Dist: sphinxcontrib-programoutput ; extra == 'dev'
Requires-Dist: coveralls (>=1.6.0) ; extra == 'dev'
Requires-Dist: draugr ; extra == 'dev'
Requires-Dist: wheel (>=0.33.0) ; extra == 'dev'
Requires-Dist: pytest-cov (>=2.6.1) ; extra == 'dev'
Provides-Extra: docs
Requires-Dist: trolls ; extra == 'docs'
Requires-Dist: mistune (<2.0.0) ; extra == 'docs'
Requires-Dist: m2r2 ; extra == 'docs'
Requires-Dist: draugr ; extra == 'docs'
Requires-Dist: sphinxcontrib-programoutput ; extra == 'docs'
Provides-Extra: setup
Requires-Dist: pytest (>=4.4.1) ; extra == 'setup'
Provides-Extra: tests
Requires-Dist: pytest (>=4.4.1) ; extra == 'tests'
